[
  {
    "name": "Edmunds, Henry Reed",
    "nicknames": [
      "Shavetail"
    ],
    "gender": "Male",
    "high school": "",
    "motto": "",
    "birthday": "",
    "hometown": "Leesburg, Fla.",
    "enrolltime": "",
    "major": "Bachelor of Science in Agriculture",
    "clubs": [
      "Ag. Club"
    ],
    "description": "A. B. Hampden-Sidney College, Va., 1905, University of Maryland, 1919-'20, 2d Lieut. Inf., U. S. A.",
    "University": "University of Florida",
    "year": 1922,
    "text": "\nA. B. Hampden-Sidney College, Va., 1905, University of Maryland, 1919-'20, 2d Lieut. Inf., U. S. A.",
    "Appearance": "0.0",
    "Character_Personality": "0.0",
    "Ability": "0.2"
  },
  {
    "name": "Emery, Sharon Odom",
    "nicknames": [
      "Odom"
    ],
    "gender": "Male",
    "high school": "",
    "motto": "",
    "birthday": "",
    "hometown": "Munson, Fla.",
    "enrolltime": "",
    "major": "Bachelor of Science in Education",
    "clubs": [
      "Ag. Club (1), (2)",
      "Peabody Club (3), (4)",
      "Student Assistant in Vocational Education",
      "Baptist Club"
    ],
    "description": "Eleven months A. E. F.",
    "University": "University of Florida",
    "year": 1922,
    "text": "\nEleven months A. E. F.",
    "Appearance": "0.0",
    "Character_Personality": "0.0",
    "Ability": "0.0"
  },
  {
    "name": "Catts, Sidney Johnston, Jr.",
    "nicknames": [
      "S. J."
    ],
    "gender": "Male",
    "high school": "",
    "motto": "",
    "birthday": "",
    "hometown": "Gainesville, Fla.",
    "enrolltime": "",
    "major": "Bachelor of Laws",
    "clubs": [
      "Theta Chi",
      "John Marshall Debating",
      "Acacia Club",
      "Law College Baseball"
    ],
    "description": "On a pathway constant with travail, Our footprints of struggling years Are left in the dust behind us, Which time erases and clears. Now crowned, gowned and honored, Sweet fruit of an earnest heart, We arise to go—yet hesitating Pause once to look back—and depart.",
    "University": "University of Florida",
    "year": 1922,
    "text": "\nOn a pathway constant with travail, Our footprints of struggling years Are left in the dust behind us, Which time erases and clears. Now crowned, gowned and honored, Sweet fruit of an earnest heart, We arise to go—yet hesitating Pause once to look back—and depart.",
    "Appearance": "0.1",
    "Character_Personality": "0.8",
    "Ability": "0.7"
  },
  {
    "name": "Royal, P. Terry",
    "nicknames": [
      "R. P."
    ],
    "gender": "Male",
    "high school": "",
    "motto": "\"He seen his duty and he done it.\"",
    "birthday": "",
    "hometown": "Jacksonville, Fla.",
    "enrolltime": "",
    "major": "Juris Doctor",
    "clubs": [],
    "description": "",
    "University": "University of Florida",
    "year": 1922,
    "text": "\"He seen his duty and he done it.\"\n",
    "Appearance": "0.0",
    "Character_Personality": "0.8",
    "Ability": "0.7"
  },
  {
    "name": "Thompson, William Earl",
    "nicknames": [
      "Thompson"
    ],
    "gender": "Male",
    "high school": "",
    "motto": "",
    "birthday": "",
    "hometown": "Tampa, Fla.",
    "enrolltime": "",
    "major": "Bachelor of Laws",
    "clubs": [
      "Theta Chi",
      "Phi Delta Phi",
      "Serpent Ribbon",
      "Business Manager Seminole",
      "John Marshall",
      "Tampa Club",
      "Inter-Collegiate Debates"
    ],
    "description": "The last recitation is over, The last class heard and tried, Our way lies east and westward On furrowless fields, world-wide. But one thing left deep in our memory As it ever was held, shall it be, Hallowed, revered and honored: Our beloved University. —F. Langworthy. 1922 PAGE 63",
    "University": "University of Florida",
    "year": 1922,
    "text": "\nThe last recitation is over, The last class heard and tried, Our way lies east and westward On furrowless fields, world-wide. But one thing left deep in our memory As it ever was held, shall it be, Hallowed, revered and honored: Our beloved University. —F. Langworthy. 1922 PAGE 63",
    "Appearance": "0.0",
    "Character_Personality": "0.0",
    "Ability": "0.0"
  }
]